[{"paperId": "3673bccde93025e05431a2bcac4e8ff18c9c273a", "publicationVenue": {"id": "30a8645d-22d4-42e2-b3f6-304bf4ce3a02", "name": "International Conference on Computational Logic", "type": "conference", "alternate_names": ["CL", "Int Conf Comput Log"]}, "url": "https://www.semanticscholar.org/paper/3673bccde93025e05431a2bcac4e8ff18c9c273a", "title": "Book Review: Natural Language Processing with Python by Steven Bird, Ewan Klein, and Edward Loper", "venue": "International Conference on Computational Logic", "year": 2009, "citationCount": 1651, "fieldsOfStudy": ["Art", "Computer Science"], "authors": [{"authorId": "2262848350", "name": "Michael Elhadad"}]}]