{
  "authorId": "144035647",
  "name": "I. Trofimov",
  "affiliations": [],
  "paperCount": 26,
  "citationCount": 351,
  "hIndex": 10,
  "papers": [
    {
      "paperId": "ea0ba110d34bfa1bed1b1919a3bb367f84bdfa38",
      "publicationVenue": {
        "id": "1901e811-ee72-4b20-8f7e-de08cd395a10",
        "name": "arXiv.org",
        "alternate_names": [
          "ArXiv"
        ],
        "issn": "2331-8422",
        "url": "https://arxiv.org"
      },
      "url": "https://www.semanticscholar.org/paper/ea0ba110d34bfa1bed1b1919a3bb367f84bdfa38",
      "title": "RTD-Lite: Scalable Topological Analysis for Comparing Weighted Graphs in Learning Tasks",
      "venue": "arXiv.org",
      "year": 2025,
      "citationCount": 0,
      "fieldsOfStudy": [
        "Computer Science",
        "Mathematics"
      ],
      "authors": [
        {
          "authorId": "2165662874",
          "name": "Eduard Tulchinskii"
        },
        {
          "authorId": "2310697178",
          "name": "Daria Voronkova"
        },
        {
          "authorId": "144035647",
          "name": "I. Trofimov"
        },
        {
          "authorId": "2293496122",
          "name": "E. Burnaev"
        },
        {
          "authorId": "2293520623",
          "name": "S. Barannikov"
        }
      ]
    },
    {
      "paperId": "1358575e14d3262b969584d3535bd7746a1737fa",
      "publicationVenue": {
        "id": "2633f5b2-c15c-49fe-80f5-07523e770c26",
        "name": "IEEE Access",
        "type": "journal",
        "issn": "2169-3536",
        "url": "http://www.ieee.org/publications_standards/publications/ieee_access.html",
        "alternate_urls": [
          "http://ieeexplore.ieee.org/servlet/opac?punumber=6287639"
        ]
      },
      "url": "https://www.semanticscholar.org/paper/1358575e14d3262b969584d3535bd7746a1737fa",
      "title": "SeqNAS: Neural Architecture Search for Event Sequence Classification",
      "venue": "IEEE Access",
      "year": 2024,
      "citationCount": 5,
      "fieldsOfStudy": [
        "Computer Science"
      ],
      "authors": [
        {
          "authorId": "2277949112",
          "name": "Igor Udovichenko"
        },
        {
          "authorId": "2183482391",
          "name": "Egor Shvetsov"
        },
        {
          "authorId": "2277952978",
          "name": "Denis Divitsky"
        },
        {
          "authorId": "2277953050",
          "name": "Dmitry Osin"
        },
        {
          "authorId": "144035647",
          "name": "I. Trofimov"
        },
        {
          "authorId": "96253241",
          "name": "I. Sukharev"
        },
        {
          "authorId": "2277952366",
          "name": "Anatoliy Glushenko"
        },
        {
          "authorId": "1490643393",
          "name": "Dmitry Berestnev"
        },
        {
          "authorId": "2257279157",
          "name": "E. Burnaev"
        }
      ]
    },
    {
      "paperId": "33a801a7e53fcbc11011a6924a9901848d6709ee",
      "publicationVenue": {
        "id": "167fa0ca-e88a-4ef7-a16f-bc66c457c806",
        "name": "European Conference on Computer Vision",
        "type": "conference",
        "alternate_names": [
          "ECCV",
          "Eur Conf Comput Vis"
        ],
        "url": "https://link.springer.com/conference/eccv"
      },
      "url": "https://www.semanticscholar.org/paper/33a801a7e53fcbc11011a6924a9901848d6709ee",
      "title": "Scalar Function Topology Divergence: Comparing Topology of 3D Objects",
      "venue": "European Conference on Computer Vision",
      "year": 2024,
      "citationCount": 0,
      "fieldsOfStudy": [
        "Computer Science",
        "Mathematics"
      ],
      "authors": [
        {
          "authorId": "144035647",
          "name": "I. Trofimov"
        },
        {
          "authorId": "2310697178",
          "name": "Daria Voronkova"
        },
        {
          "authorId": "2165662874",
          "name": "Eduard Tulchinskii"
        },
        {
          "authorId": "2257279157",
          "name": "E. Burnaev"
        },
        {
          "authorId": "101098891",
          "name": "S. Barannikov"
        }
      ]
    },
    {
      "paperId": "4ee6e1d2dd655c722f9b0bfbf991658a236a1029",
      "publicationVenue": {
        "id": "2633f5b2-c15c-49fe-80f5-07523e770c26",
        "name": "IEEE Access",
        "type": "journal",
        "issn": "2169-3536",
        "url": "http://www.ieee.org/publications_standards/publications/ieee_access.html",
        "alternate_urls": [
          "http://ieeexplore.ieee.org/servlet/opac?punumber=6287639"
        ]
      },
      "url": "https://www.semanticscholar.org/paper/4ee6e1d2dd655c722f9b0bfbf991658a236a1029",
      "title": "A Large-Scale Empirical Study of Aligned Time Series Forecasting",
      "venue": "IEEE Access",
      "year": 2024,
      "citationCount": 0,
      "fieldsOfStudy": [
        "Computer Science"
      ],
      "authors": [
        {
          "authorId": "138609337",
          "name": "Polina Pilyugina"
        },
        {
          "authorId": "2320930610",
          "name": "Svetlana Medvedeva"
        },
        {
          "authorId": "2180163778",
          "name": "Kirill Mosievich"
        },
        {
          "authorId": "144035647",
          "name": "I. Trofimov"
        },
        {
          "authorId": "2290006588",
          "name": "Alina Kostromina"
        },
        {
          "authorId": "2125682227",
          "name": "Dmitry Simakov"
        },
        {
          "authorId": "2257279157",
          "name": "E. Burnaev"
        }
      ]
    },
    {
      "paperId": "d7ff83cb989e5bdf7b9de766e235c37394614189",
      "publicationVenue": {
        "id": "fc0a208c-acb7-47dc-a0d4-af8190e21d29",
        "name": "International Conference on Machine Learning",
        "type": "conference",
        "alternate_names": [
          "ICML",
          "Int Conf Mach Learn"
        ],
        "url": "https://icml.cc/"
      },
      "url": "https://www.semanticscholar.org/paper/d7ff83cb989e5bdf7b9de766e235c37394614189",
      "title": "Disentanglement Learning via Topology",
      "venue": "International Conference on Machine Learning",
      "year": 2023,
      "citationCount": 2,
      "fieldsOfStudy": [
        "Computer Science",
        "Mathematics"
      ],
      "authors": [
        {
          "authorId": "2148757496",
          "name": "Nikita Balabin"
        },
        {
          "authorId": "2310697178",
          "name": "Daria Voronkova"
        },
        {
          "authorId": "144035647",
          "name": "I. Trofimov"
        },
        {
          "authorId": "51139941",
          "name": "Evgeny Burnaev"
        },
        {
          "authorId": "101098891",
          "name": "S. Barannikov"
        }
      ]
    },
    {
      "paperId": "e2f69d96c20acce19ca53a4086d9ac702237cead",
      "publicationVenue": {
        "id": "939c6e1d-0d17-4d6e-8a82-66d960df0e40",
        "name": "International Conference on Learning Representations",
        "type": "conference",
        "alternate_names": [
          "Int Conf Learn Represent",
          "ICLR"
        ],
        "url": "https://iclr.cc/"
      },
      "url": "https://www.semanticscholar.org/paper/e2f69d96c20acce19ca53a4086d9ac702237cead",
      "title": "Learning Topology-Preserving Data Representations",
      "venue": "International Conference on Learning Representations",
      "year": 2023,
      "citationCount": 17,
      "fieldsOfStudy": [
        "Computer Science",
        "Mathematics"
      ],
      "authors": [
        {
          "authorId": "144035647",
          "name": "I. Trofimov"
        },
        {
          "authorId": "2037913268",
          "name": "Daniil Cherniavskii"
        },
        {
          "authorId": "2165662874",
          "name": "Eduard Tulchinskii"
        },
        {
          "authorId": "2148757496",
          "name": "Nikita Balabin"
        },
        {
          "authorId": "51139941",
          "name": "Evgeny Burnaev"
        },
        {
          "authorId": "101098891",
          "name": "S. Barannikov"
        }
      ]
    },
    {
      "paperId": "34fdc39b943c49be654b499ace271099e1cc2766",
      "publicationVenue": {
        "id": "2633f5b2-c15c-49fe-80f5-07523e770c26",
        "name": "IEEE Access",
        "type": "journal",
        "issn": "2169-3536",
        "url": "http://www.ieee.org/publications_standards/publications/ieee_access.html",
        "alternate_urls": [
          "http://ieeexplore.ieee.org/servlet/opac?punumber=6287639"
        ]
      },
      "url": "https://www.semanticscholar.org/paper/34fdc39b943c49be654b499ace271099e1cc2766",
      "title": "Learned Query Optimizers: Evaluation and Improvement",
      "venue": "IEEE Access",
      "year": 2022,
      "citationCount": 7,
      "fieldsOfStudy": [
        "Computer Science"
      ],
      "authors": [
        {
          "authorId": "2176320619",
          "name": "Artem Mikhaylov"
        },
        {
          "authorId": "1557382779",
          "name": "Nina Mazyavkina"
        },
        {
          "authorId": "49614468",
          "name": "Mikhail Salnikov"
        },
        {
          "authorId": "144035647",
          "name": "I. Trofimov"
        },
        {
          "authorId": "2176324412",
          "name": "Fu Qiang"
        },
        {
          "authorId": "51139941",
          "name": "Evgeny Burnaev"
        }
      ]
    },
    {
      "paperId": "425a8b4dc4da3c1a47b68c885cc1461c0368a06a",
      "publicationVenue": {
        "id": "c4e26c05-cc78-4a34-9cc8-567aa54a8877",
        "name": "International Conference on Machine Vision",
        "type": "conference",
        "alternate_names": [
          "Int Conf Mach Vis",
          "ICMV"
        ]
      },
      "url": "https://www.semanticscholar.org/paper/425a8b4dc4da3c1a47b68c885cc1461c0368a06a",
      "title": "Homological assessment of data representations",
      "venue": "International Conference on Machine Vision",
      "year": 2022,
      "citationCount": 1,
      "fieldsOfStudy": [
        "Computer Science"
      ],
      "authors": [
        {
          "authorId": "101098891",
          "name": "S. Barannikov"
        },
        {
          "authorId": "144035647",
          "name": "I. Trofimov"
        },
        {
          "authorId": "2107696597",
          "name": "Ekaterina Trimbach"
        },
        {
          "authorId": "66063792",
          "name": "J. Wang"
        },
        {
          "authorId": "51139941",
          "name": "Evgeny Burnaev"
        }
      ]
    },
    {
      "paperId": "44ba12d5bb4eac3602752ee40c36cdbedecab949",
      "publicationVenue": {
        "id": "8e1bd4b5-d5b2-4e22-ba0a-01fe5568d472",
        "name": "Remote Sensing",
        "type": "journal",
        "alternate_names": [
          "Remote Sens"
        ],
        "issn": "2315-4675",
        "alternate_issns": [
          "2072-4292"
        ],
        "url": "http://www.e-helvetica.nb.admin.ch/directAccess?callnumber=bel-169233",
        "alternate_urls": [
          "https://www.mdpi.com/journal/remotesensing",
          "http://www.mdpi.com/journal/remotesensing",
          "http://nbn-resolving.de/urn/resolver.pl?urn=urn:nbn:ch:bel-169233"
        ]
      },
      "url": "https://www.semanticscholar.org/paper/44ba12d5bb4eac3602752ee40c36cdbedecab949",
      "title": "Data-Driven Short-Term Daily Operational Sea Ice Regional Forecasting",
      "venue": "Remote Sensing",
      "year": 2022,
      "citationCount": 14,
      "fieldsOfStudy": [
        "Computer Science"
      ],
      "authors": [
        {
          "authorId": "2187931756",
          "name": "Timofey Grigoryev"
        },
        {
          "authorId": "74925695",
          "name": "P. Verezemskaya"
        },
        {
          "authorId": "71321048",
          "name": "Mikhail Krinitskiy"
        },
        {
          "authorId": "2096712324",
          "name": "N. Anikin"
        },
        {
          "authorId": "94542669",
          "name": "A. Gavrikov"
        },
        {
          "authorId": "144035647",
          "name": "I. Trofimov"
        },
        {
          "authorId": "2148757496",
          "name": "Nikita Balabin"
        },
        {
          "authorId": "35431760",
          "name": "A. Shpilman"
        },
        {
          "authorId": "2187931753",
          "name": "Andrei Eremchenko"
        },
        {
          "authorId": "6783941",
          "name": "S. Gulev"
        },
        {
          "authorId": "51139941",
          "name": "Evgeny Burnaev"
        },
        {
          "authorId": "2279838358",
          "name": "V. Vanovski\u00fd"
        }
      ]
    },
    {
      "paperId": "a317361dec4cde37d2e24982fada9da30796e4bb",
      "publicationVenue": {
        "id": "2633f5b2-c15c-49fe-80f5-07523e770c26",
        "name": "IEEE Access",
        "type": "journal",
        "issn": "2169-3536",
        "url": "http://www.ieee.org/publications_standards/publications/ieee_access.html",
        "alternate_urls": [
          "http://ieeexplore.ieee.org/servlet/opac?punumber=6287639"
        ]
      },
      "url": "https://www.semanticscholar.org/paper/a317361dec4cde37d2e24982fada9da30796e4bb",
      "title": "QuantNAS for Super Resolution: Searching for Efficient Quantization-Friendly Architectures Against Quantization Noise",
      "venue": "IEEE Access",
      "year": 2022,
      "citationCount": 2,
      "fieldsOfStudy": [
        "Computer Science"
      ],
      "authors": [
        {
          "authorId": "2183482391",
          "name": "Egor Shvetsov"
        },
        {
          "authorId": "46561836",
          "name": "D. Osin"
        },
        {
          "authorId": "122998174",
          "name": "A. Zaytsev"
        },
        {
          "authorId": "2018128",
          "name": "Ivan Koryakovskiy"
        },
        {
          "authorId": "2183483650",
          "name": "Valentin Buchnev"
        },
        {
          "authorId": "144035647",
          "name": "I. Trofimov"
        },
        {
          "authorId": "51139941",
          "name": "Evgeny Burnaev"
        }
      ]
    },
    {
      "paperId": "382cb9142fbeb6aeae41e720a0d3040cb997be0e",
      "publicationVenue": {
        "id": "d9720b90-d60b-48bc-9df8-87a30b9a60dd",
        "name": "Neural Information Processing Systems",
        "type": "conference",
        "alternate_names": [
          "Neural Inf Process Syst",
          "NeurIPS",
          "NIPS"
        ],
        "url": "http://neurips.cc/"
      },
      "url": "https://www.semanticscholar.org/paper/382cb9142fbeb6aeae41e720a0d3040cb997be0e",
      "title": "Manifold Topology Divergence: a Framework for Comparing Data Manifolds",
      "venue": "Neural Information Processing Systems",
      "year": 2021,
      "citationCount": 24,
      "fieldsOfStudy": [
        "Computer Science",
        "Mathematics"
      ],
      "authors": [
        {
          "authorId": "101098891",
          "name": "S. Barannikov"
        },
        {
          "authorId": "144035647",
          "name": "I. Trofimov"
        },
        {
          "authorId": "2043234347",
          "name": "Grigorii Sotnikov"
        },
        {
          "authorId": "2107696597",
          "name": "Ekaterina Trimbach"
        },
        {
          "authorId": "145750616",
          "name": "Alexander Korotin"
        },
        {
          "authorId": "8792436",
          "name": "Alexander N. Filippov"
        },
        {
          "authorId": "51139941",
          "name": "Evgeny Burnaev"
        }
      ]
    },
    {
      "paperId": "655e4837a05afdfa03124d9c41c0912805423571",
      "publicationVenue": {
        "id": "fc0a208c-acb7-47dc-a0d4-af8190e21d29",
        "name": "International Conference on Machine Learning",
        "type": "conference",
        "alternate_names": [
          "ICML",
          "Int Conf Mach Learn"
        ],
        "url": "https://icml.cc/"
      },
      "url": "https://www.semanticscholar.org/paper/655e4837a05afdfa03124d9c41c0912805423571",
      "title": "Representation Topology Divergence: A Method for Comparing Neural Network Representations",
      "venue": "International Conference on Machine Learning",
      "year": 2021,
      "citationCount": 43,
      "fieldsOfStudy": [
        "Computer Science",
        "Mathematics"
      ],
      "authors": [
        {
          "authorId": "101098891",
          "name": "S. Barannikov"
        },
        {
          "authorId": "144035647",
          "name": "I. Trofimov"
        },
        {
          "authorId": "2148757496",
          "name": "Nikita Balabin"
        },
        {
          "authorId": "51139941",
          "name": "Evgeny Burnaev"
        }
      ]
    },
    {
      "paperId": "2986076057868fe037a7c956543e13dc772f2bf6",
      "publicationVenue": {
        "id": "2633f5b2-c15c-49fe-80f5-07523e770c26",
        "name": "IEEE Access",
        "type": "journal",
        "issn": "2169-3536",
        "url": "http://www.ieee.org/publications_standards/publications/ieee_access.html",
        "alternate_urls": [
          "http://ieeexplore.ieee.org/servlet/opac?punumber=6287639"
        ]
      },
      "url": "https://www.semanticscholar.org/paper/2986076057868fe037a7c956543e13dc772f2bf6",
      "title": "Multi-Fidelity Neural Architecture Search With Knowledge Distillation",
      "venue": "IEEE Access",
      "year": 2020,
      "citationCount": 15,
      "fieldsOfStudy": [
        "Computer Science",
        "Mathematics"
      ],
      "authors": [
        {
          "authorId": "144035647",
          "name": "I. Trofimov"
        },
        {
          "authorId": "143888131",
          "name": "Nikita Klyuchnikov"
        },
        {
          "authorId": "49614468",
          "name": "Mikhail Salnikov"
        },
        {
          "authorId": "8792436",
          "name": "Alexander N. Filippov"
        },
        {
          "authorId": "51139941",
          "name": "Evgeny Burnaev"
        }
      ]
    },
    {
      "paperId": "2bb6a9ce2947dd74db6b40d57f0bb094d6f25e6f",
      "publicationVenue": {
        "id": "1901e811-ee72-4b20-8f7e-de08cd395a10",
        "name": "arXiv.org",
        "alternate_names": [
          "ArXiv"
        ],
        "issn": "2331-8422",
        "url": "https://arxiv.org"
      },
      "url": "https://www.semanticscholar.org/paper/2bb6a9ce2947dd74db6b40d57f0bb094d6f25e6f",
      "title": "Topological obstructions in neural networks learning",
      "venue": "arXiv.org",
      "year": 2020,
      "citationCount": 6,
      "fieldsOfStudy": [
        "Computer Science",
        "Mathematics"
      ],
      "authors": [
        {
          "authorId": "101098891",
          "name": "S. Barannikov"
        },
        {
          "authorId": "2043234347",
          "name": "Grigorii Sotnikov"
        },
        {
          "authorId": "144035647",
          "name": "I. Trofimov"
        },
        {
          "authorId": "145750616",
          "name": "Alexander Korotin"
        },
        {
          "authorId": "51139941",
          "name": "Evgeny Burnaev"
        }
      ]
    },
    {
      "paperId": "384018a47a27ef0b1b4b073676dcc75b8e59a77f",
      "publicationVenue": {
        "id": "e12d355b-ad1e-428d-ba3e-8373fd3a7bd8",
        "name": "Sai",
        "type": "conference",
        "alternate_names": [
          "Science and Information Conference",
          "Sci Inf Conf",
          "SAI"
        ],
        "issn": "1975-7743",
        "url": "http://www.koreanst.org/"
      },
      "url": "https://www.semanticscholar.org/paper/384018a47a27ef0b1b4b073676dcc75b8e59a77f",
      "title": "Optimizing the Neural Architecture of Reinforcement Learning Agents",
      "venue": "Sai",
      "year": 2020,
      "citationCount": 4,
      "fieldsOfStudy": [
        "Computer Science"
      ],
      "authors": [
        {
          "authorId": "1557382779",
          "name": "Nina Mazyavkina"
        },
        {
          "authorId": "122147195",
          "name": "S. Moustafa"
        },
        {
          "authorId": "144035647",
          "name": "I. Trofimov"
        },
        {
          "authorId": "2859754",
          "name": "E. Burnaev"
        }
      ]
    },
    {
      "paperId": "48167fbde4ef8d5caa69e1c0c9d6e2ac7fd48c3b",
      "publicationVenue": {
        "id": "2633f5b2-c15c-49fe-80f5-07523e770c26",
        "name": "IEEE Access",
        "type": "journal",
        "issn": "2169-3536",
        "url": "http://www.ieee.org/publications_standards/publications/ieee_access.html",
        "alternate_urls": [
          "http://ieeexplore.ieee.org/servlet/opac?punumber=6287639"
        ]
      },
      "url": "https://www.semanticscholar.org/paper/48167fbde4ef8d5caa69e1c0c9d6e2ac7fd48c3b",
      "title": "NAS-Bench-NLP: Neural Architecture Search Benchmark for Natural Language Processing",
      "venue": "IEEE Access",
      "year": 2020,
      "citationCount": 97,
      "fieldsOfStudy": [
        "Computer Science",
        "Mathematics"
      ],
      "authors": [
        {
          "authorId": "143888131",
          "name": "Nikita Klyuchnikov"
        },
        {
          "authorId": "144035647",
          "name": "I. Trofimov"
        },
        {
          "authorId": "13033978",
          "name": "E. Artemova"
        },
        {
          "authorId": "49614468",
          "name": "Mikhail Salnikov"
        },
        {
          "authorId": "143954683",
          "name": "M. Fedorov"
        },
        {
          "authorId": "51139941",
          "name": "Evgeny Burnaev"
        }
      ]
    },
    {
      "paperId": "a85bdb07426ce5820129b23ee65e338372603927",
      "publicationVenue": null,
      "url": "https://www.semanticscholar.org/paper/a85bdb07426ce5820129b23ee65e338372603927",
      "title": "The Machine Learning Algorithm for Solving the Problem of Generating Recommendations for Goods and Services",
      "venue": "",
      "year": 2020,
      "citationCount": 0,
      "fieldsOfStudy": [
        "Computer Science"
      ],
      "authors": [
        {
          "authorId": "32400580",
          "name": "V. Sudakov"
        },
        {
          "authorId": "144035647",
          "name": "I. Trofimov"
        }
      ]
    },
    {
      "paperId": "1d785525800860d219b8c299d72e65c57081132e",
      "publicationVenue": {
        "id": "1901e811-ee72-4b20-8f7e-de08cd395a10",
        "name": "arXiv.org",
        "alternate_names": [
          "ArXiv"
        ],
        "issn": "2331-8422",
        "url": "https://arxiv.org"
      },
      "url": "https://www.semanticscholar.org/paper/1d785525800860d219b8c299d72e65c57081132e",
      "title": "Inferring Complementary Products from Baskets and Browsing Sessions",
      "venue": "arXiv.org",
      "year": 2018,
      "citationCount": 13,
      "fieldsOfStudy": [
        "Computer Science",
        "Mathematics"
      ],
      "authors": [
        {
          "authorId": "144035647",
          "name": "I. Trofimov"
        }
      ]
    },
    {
      "paperId": "b7b428aa7286acd982e1925d3cc70cf49cdbd6ca",
      "publicationVenue": {
        "id": "1901e811-ee72-4b20-8f7e-de08cd395a10",
        "name": "arXiv.org",
        "alternate_names": [
          "ArXiv"
        ],
        "issn": "2331-8422",
        "url": "https://arxiv.org"
      },
      "url": "https://www.semanticscholar.org/paper/b7b428aa7286acd982e1925d3cc70cf49cdbd6ca",
      "title": "LHCb trigger streams optimization",
      "venue": "arXiv.org",
      "year": 2017,
      "citationCount": 2,
      "fieldsOfStudy": [
        "Computer Science",
        "Physics"
      ],
      "authors": [
        {
          "authorId": "3581989",
          "name": "D. Derkach"
        },
        {
          "authorId": "3258069",
          "name": "N. Kazeev"
        },
        {
          "authorId": "9540523",
          "name": "R. Neychev"
        },
        {
          "authorId": "2139994859",
          "name": "A. Panin"
        },
        {
          "authorId": "144035647",
          "name": "I. Trofimov"
        },
        {
          "authorId": "2313258448",
          "name": "Andrey Ustyuzhanin"
        },
        {
          "authorId": "145466813",
          "name": "M. Vesterinen"
        }
      ]
    },
    {
      "paperId": "af993fce7868f23845d006faa4c689c9cca868cd",
      "publicationVenue": {
        "id": "c95e79f8-dc6a-45e2-8413-c9c90694a216",
        "name": "Pattern Recognition and Image Analysis",
        "type": "journal",
        "alternate_names": [
          "Pattern Recognit Image Anal"
        ],
        "issn": "1054-6618",
        "url": "https://link.springer.com/journal/11493"
      },
      "url": "https://www.semanticscholar.org/paper/af993fce7868f23845d006faa4c689c9cca868cd",
      "title": "Distributed coordinate descent for generalized linear models with regularization",
      "venue": "Pattern Recognition and Image Analysis",
      "year": 2016,
      "citationCount": 7,
      "fieldsOfStudy": [
        "Mathematics",
        "Computer Science"
      ],
      "authors": [
        {
          "authorId": "144035647",
          "name": "I. Trofimov"
        },
        {
          "authorId": "143629224",
          "name": "A. Genkin"
        }
      ]
    },
    {
      "paperId": "9205e0f6dcc9899dcbc405dfc2a3b4ad1b4b7c74",
      "publicationVenue": null,
      "url": "https://www.semanticscholar.org/paper/9205e0f6dcc9899dcbc405dfc2a3b4ad1b4b7c74",
      "title": "Solving the Choice Problem in the Conditions of Physical Diversity and Limited Observable Signs",
      "venue": "",
      "year": 2015,
      "citationCount": 0,
      "fieldsOfStudy": [
        "Computer Science"
      ],
      "authors": [
        {
          "authorId": "13059257",
          "name": "V. Arseniev"
        },
        {
          "authorId": "144035647",
          "name": "I. Trofimov"
        }
      ]
    },
    {
      "paperId": "58f2d0015be66fec248ef1e5d29b640e08a4dee9",
      "publicationVenue": {
        "id": "177c6304-7683-4881-bc71-3c1811df53f0",
        "name": "International Joint Conference on the Analysis of Images, Social Networks and Texts",
        "type": "conference",
        "alternate_names": [
          "AIST",
          "Int Jt Conf Anal Image Soc Netw Text"
        ]
      },
      "url": "https://www.semanticscholar.org/paper/58f2d0015be66fec248ef1e5d29b640e08a4dee9",
      "title": "Distributed Coordinate Descent for L1-regularized Logistic Regression",
      "venue": "International Joint Conference on the Analysis of Images, Social Networks and Texts",
      "year": 2014,
      "citationCount": 15,
      "fieldsOfStudy": [
        "Mathematics",
        "Computer Science"
      ],
      "authors": [
        {
          "authorId": "144035647",
          "name": "I. Trofimov"
        },
        {
          "authorId": "143629224",
          "name": "A. Genkin"
        }
      ]
    },
    {
      "paperId": "8b8e140db6e7c026e065f9b28d0232be107558ee",
      "publicationVenue": {
        "id": "1901e811-ee72-4b20-8f7e-de08cd395a10",
        "name": "arXiv.org",
        "alternate_names": [
          "ArXiv"
        ],
        "issn": "2331-8422",
        "url": "https://arxiv.org"
      },
      "url": "https://www.semanticscholar.org/paper/8b8e140db6e7c026e065f9b28d0232be107558ee",
      "title": "Using Neural Networks for Click Prediction of Sponsored Search",
      "venue": "arXiv.org",
      "year": 2014,
      "citationCount": 12,
      "fieldsOfStudy": [
        "Computer Science"
      ],
      "authors": [
        {
          "authorId": "1925166",
          "name": "Afroze Ibrahim Baqapuri"
        },
        {
          "authorId": "144035647",
          "name": "I. Trofimov"
        }
      ]
    },
    {
      "paperId": "eeda2e2266147b1ebbd9b24aa2f611cdcf2b640f",
      "publicationVenue": {
        "id": "8dce23a9-44e0-4381-a39e-2acc1edff700",
        "name": "Annual International ACM SIGIR Conference on Research and Development in Information Retrieval",
        "type": "conference",
        "alternate_names": [
          "International ACM SIGIR Conference on Research and Development in Information Retrieval",
          "Int ACM SIGIR Conf Res Dev Inf Retr",
          "SIGIR",
          "Annu Int ACM SIGIR Conf Res Dev Inf Retr"
        ],
        "url": "http://www.acm.org/sigir/"
      },
      "url": "https://www.semanticscholar.org/paper/eeda2e2266147b1ebbd9b24aa2f611cdcf2b640f",
      "title": "On peculiarities of positional effects in sponsored search",
      "venue": "Annual International ACM SIGIR Conference on Research and Development in Information Retrieval",
      "year": 2014,
      "citationCount": 3,
      "fieldsOfStudy": [
        "Computer Science"
      ],
      "authors": [
        {
          "authorId": "47078900",
          "name": "Vyacheslav Alipov"
        },
        {
          "authorId": "2194770",
          "name": "Valery A. Topinsky"
        },
        {
          "authorId": "144035647",
          "name": "I. Trofimov"
        }
      ]
    },
    {
      "paperId": "9987508700bd2c3c8d6ad175edf8159668268417",
      "publicationVenue": {
        "id": "e07422f9-c065-40c3-a37b-75e98dce79fe",
        "name": "The Web Conference",
        "type": "conference",
        "alternate_names": [
          "Web Conf",
          "WWW"
        ],
        "url": "http://www.iw3c2.org/"
      },
      "url": "https://www.semanticscholar.org/paper/9987508700bd2c3c8d6ad175edf8159668268417",
      "title": "New features for query dependent sponsored search click prediction",
      "venue": "The Web Conference",
      "year": 2013,
      "citationCount": 2,
      "fieldsOfStudy": [
        "Computer Science"
      ],
      "authors": [
        {
          "authorId": "144035647",
          "name": "I. Trofimov"
        }
      ]
    },
    {
      "paperId": "2570a4f8ad979303dd4817e4b42bf8003aaa0344",
      "publicationVenue": {
        "id": "e1ab4e9b-5586-4645-bb70-e53e42367ffe",
        "name": "International Workshop on Data Mining for Online Advertising",
        "type": "conference",
        "alternate_names": [
          "ADKDD",
          "Int Workshop Data Min Online Advert"
        ]
      },
      "url": "https://www.semanticscholar.org/paper/2570a4f8ad979303dd4817e4b42bf8003aaa0344",
      "title": "Using boosted trees for click-through rate prediction for sponsored search",
      "venue": "International Workshop on Data Mining for Online Advertising",
      "year": 2012,
      "citationCount": 64,
      "fieldsOfStudy": [
        "Computer Science"
      ],
      "authors": [
        {
          "authorId": "144035647",
          "name": "I. Trofimov"
        },
        {
          "authorId": "4306439",
          "name": "A. Kornetova"
        },
        {
          "authorId": "1397376957",
          "name": "Valery Topinskiy"
        }
      ]
    }
  ]
}